radikopodcast/__init__.py
radikopodcast/cli.py
radikopodcast/config.py
radikopodcast/exceptions.py
radikopodcast/py.typed
radikopodcast/radiko_archiver.py
radikopodcast/radiko_datetime.py
radikopodcast/radiko_podcast.py
radikopodcast/radiko_stream_spec_factory.py
radikopodcast/database/__init__.py
radikopodcast/database/database.py
radikopodcast/database/models.py
radikopodcast/database/program_downloader.py
radikopodcast/database/program_schedule.py
radikopodcast/database/session_manager.py
radikopodcast/radikoapi/__init__.py
radikopodcast/radikoapi/radiko_api.py
radikopodcast/radikoapi/requester.py
radikopodcast/radikoxml/__init__.py
radikopodcast/radikoxml/xml_converter.py
radikopodcast/radikoxml/xml_parser.py
radikopodcast-1.0.3.dist-info/LICENSE
radikopodcast-1.0.3.dist-info/METADATA
radikopodcast-1.0.3.dist-info/WHEEL
radikopodcast-1.0.3.dist-info/entry_points.txt
radikopodcast-1.0.3.dist-info/top_level.txt
radikopodcast-1.0.3.dist-info/RECORD
