Metadata-Version: 2.1
Name: radikopodcast
Version: 1.0.3
Summary: Automatic archiver for radiko program which queried by YAML file.
Author-email: Master <roadmasternavi@gmail.com>
Maintainer-email: Master <roadmasternavi@gmail.com>
License: MIT License
Project-URL: homepage, https://github.com/road-master/radiko-podcast
Project-URL: repository, https://github.com/road-master/radiko-podcast
Keywords: radiko,radikopodcast
Classifier: Development Status :: 5 - Production/Stable
Classifier: Environment :: Console
Classifier: Intended Audience :: End Users/Desktop
Classifier: License :: OSI Approved :: MIT License
Classifier: Natural Language :: English
Classifier: Operating System :: OS Independent
Classifier: Programming Language :: Python
Classifier: Programming Language :: Python :: 3
Classifier: Programming Language :: Python :: 3.9
Classifier: Programming Language :: Python :: 3.10
Classifier: Programming Language :: Python :: 3.11
Classifier: Programming Language :: Python :: 3.12
Classifier: Topic :: Internet
Classifier: Topic :: Internet :: WWW/HTTP
Classifier: Topic :: Internet :: WWW/HTTP :: Indexing/Search
Classifier: Topic :: Multimedia
Classifier: Topic :: Multimedia :: Sound/Audio
Classifier: Topic :: Multimedia :: Sound/Audio :: Capture/Recording
Classifier: Topic :: System
Classifier: Topic :: System :: Archiving
Classifier: Topic :: System :: Archiving :: Backup
Classifier: Topic :: System :: Filesystems
Classifier: Typing :: Typed
Requires-Python: >=3.9
License-File: LICENSE
Requires-Dist: click
Requires-Dist: errorcollector
Requires-Dist: ffmpeg-python
Requires-Dist: radikoplaylist
Requires-Dist: yamldataclassconfig
Requires-Dist: sqlalchemy <2.0.0
Requires-Dist: inflector
Requires-Dist: asynccpu
Requires-Dist: asyncffmpeg
Requires-Dist: defusedxml
Provides-Extra: test
